lesscode_pay/__init__.py
lesscode_pay/wx/__init__.py
lesscode_pay/wx/v2/__init__.py
lesscode_pay/wx/v2/common_api.py
lesscode_pay/wx/v3/__init__.py
lesscode_pay/wx/v3/app_api.py
lesscode_pay/wx/v3/common_api.py
lesscode_pay/wx/v3/common_combine_api.py
lesscode_pay/wx/v3/h5_api.py
lesscode_pay/wx/v3/js_api.py
lesscode_pay/wx/v3/native_api.py
lesscode_pay/zfb/__init__.py
lesscode_pay-0.0.1.dist-info/METADATA
lesscode_pay-0.0.1.dist-info/WHEEL
lesscode_pay-0.0.1.dist-info/licenses/LICENSE
lesscode_pay-0.0.1.dist-info/RECORD
