Metadata-Version: 2.1
Name: lesscode-pay
Version: 0.0.1
Summary: 统一的低代码支付SDK
Author-email: navysummer <navysummer@yeah.net>
License: MIT License
License-File: LICENSE
Classifier: License :: OSI Approved :: MIT License
Classifier: Operating System :: OS Independent
Classifier: Programming Language :: Python :: 3
Requires-Python: >=3.7
Requires-Dist: cryptography>=44.0.2
Requires-Dist: requests>=2.31.0
Requires-Dist: xmltodict>=0.14.2
